qload/__init__.py
qload/base.py
qload/driver.py
qload/exception.py
qload/expression.py
qload-1.0.3.dist-info/METADATA
qload-1.0.3.dist-info/WHEEL
qload-1.0.3.dist-info/RECORD
