Metadata-Version: 2.1
Name: qload
Version: 1.0.3
Summary: python library to perform assertion on files
License: MIT
Author: Fabien Arcellier
Author-email: fabien.arcellier@gmail.com
Requires-Python: >=3.8,<4.0
Classifier: License :: OSI Approved :: MIT License
Classifier: Programming Language :: Python :: 3
Classifier: Programming Language :: Python :: 3.8
Classifier: Programming Language :: Python :: 3.9
Classifier: Programming Language :: Python :: 3.10
Classifier: Programming Language :: Python :: 3.11
Classifier: Programming Language :: Python :: 3.12
Requires-Dist: boto3 (>=1.26.34,<2.0.0)
Requires-Dist: ftputil (>=5.0.4,<6.0.0)
Requires-Dist: jmespath (>=1.0.1,<2.0.0)
Requires-Dist: jsonpath-ng (>=1.5.3,<2.0.0)
Requires-Dist: pandas (>=2.0.1,<3.0.0)
Requires-Dist: pyarrow (>=12.0.0)
Requires-Dist: pyyaml (>=6.0,<7.0)
Project-URL: Source, https://github.com/FabienArcellier/qload
